CHANGELOG.rst
LICENSE.txt
MANIFEST.in
README.rst
TODO.txt
VERSION.txt
setup.cfg
setup.py
secpass/__init__.py
secpass/api.py
secpass/engine.py
secpass/model.py
secpass/test_engine.py
secpass/test_helpers.py
secpass/util.py
secpass.egg-info/PKG-INFO
secpass.egg-info/SOURCES.txt
secpass.egg-info/dependency_links.txt
secpass.egg-info/entry_points.txt
secpass.egg-info/namespace_packages.txt
secpass.egg-info/not-zip-safe
secpass.egg-info/requires.txt
secpass.egg-info/top_level.txt
secpass/cli/__init__.py
secpass/cli/base.py
secpass/cli/config.py
secpass/cli/note.py
secpass/cli/pass.py
secpass/cli/test_base.py
secpass/cli/test_config.py
secpass/driver/__init__.py
secpass/driver/file.py
secpass/driver/pgpfile.py
secpass/driver/spbp.py
secpass/driver/stream.py
secpass/driver/test_file.py
secpass/driver/test_pgpfile.py
secpass/driver/test_stream.py
secpass/res/opiyum-cert-chain.pem
secpass/res/help/client-setup-risk.rst
secpass/res/help/client-setup.rst
secpass/res/help/config-default-client.id.rst
secpass/res/help/config-default-client.name.rst
secpass/res/help/config-default-client.risk.rst
secpass/res/help/config-default-locale.rst
secpass/res/help/config-default-profile.default.rst
secpass/res/help/config-driver-base-driver.rst
secpass/res/help/config-driver-base-name.rst
secpass/res/help/config-driver-file-driver.path.rst
secpass/res/help/config-driver-pgpfile-driver.agent.rst
secpass/res/help/config-driver-pgpfile-driver.path.rst
secpass/res/help/config-driver-spbp-driver.password.rst
secpass/res/help/config-driver-spbp-driver.username.rst
secpass/res/help/config-epilog.rst
secpass/res/help/config-preamble.rst
secpass/res/help/intro.rst
secpass/res/help/keygen.rst
secpass/res/help/noagent.rst
secpass/res/help/noprofile.rst
secpass/res/help/profile-create-encrypt-pgpfile-needkey.rst
secpass/res/help/profile-create-encrypt-spbp-needkey.rst
secpass/res/help/profile-create-name.rst
secpass/res/help/profile-create-options-file.rst
secpass/res/help/profile-create-options-pgpfile.rst
secpass/res/help/profile-create-options-spbp-new-vault.rst
secpass/res/help/profile-create-options-spbp-new.rst
secpass/res/help/profile-create-options-spbp.rst
secpass/res/help/profile-create-type.rst
secpass/res/help/profile-create.rst
