Metadata-Version: 1.1
Name: secpass
Version: 0.4.0
Summary: Secure Passwords
Home-page: http://github.com/metagriffin/secpass
Author: metagriffin
Author-email: mg.pypi@metagriffin.net
License: GPLv3+
Keywords: secure password manager command line library
Platform: any
Classifier: Development Status :: 4 - Beta
Classifier: Environment :: Console
Classifier: Natural Language :: English
Classifier: Operating System :: OS Independent
Classifier: Programming Language :: Python
Classifier: Intended Audience :: End Users/Desktop
Classifier: Topic :: Utilities
Classifier: Topic :: Security
Classifier: License :: OSI Approved :: GNU General Public License v3 or later (GPLv3+)
